mipa/__init__.py
mipa/_version.py
mipa/client.py
mipa/exception.py
mipa/gateway.py
mipa/http.py
mipa/router.py
mipa/state.py
mipa/utils.py
mipa/ext/__init__.py
mipa/ext/commands/__init__.py
mipa/ext/commands/_types.py
mipa/ext/commands/bot.py
mipa/ext/commands/cog.py
mipa/ext/commands/context.py
mipa/ext/commands/core.py
mipa/ext/tasks/__init__.py
mipa/ext/timelines/__init__.py
mipa/ext/timelines/core.py
mipa-0.4.5.dist-info/LICENSE
mipa-0.4.5.dist-info/METADATA
mipa-0.4.5.dist-info/WHEEL
mipa-0.4.5.dist-info/top_level.txt
mipa-0.4.5.dist-info/RECORD
