Metadata-Version: 2.2
Name: mipa
Version: 0.4.5
Summary: Python Misskey Bot Framework
Home-page: https://github.com/yupix/MiPA
Author: yupix
Author-email: yupi0982@outlook.jp
License: MIT
Classifier: Development Status :: 2 - Pre-Alpha
Classifier: Programming Language :: Python :: 3.12
Classifier: Natural Language :: Japanese
Classifier: License :: OSI Approved :: MIT License
Requires-Python: >=3.12, <4.0
License-File: LICENSE
Requires-Dist: aiohttp==3.9.1
Requires-Dist: mipac<0.8.0,>=0.7.0
Requires-Dist: versioneer
Provides-Extra: dev
Requires-Dist: ruff; extra == "dev"
Requires-Dist: isort; extra == "dev"
Requires-Dist: mypy; extra == "dev"
Requires-Dist: flake8; extra == "dev"
Provides-Extra: ci
Requires-Dist: flake8; extra == "ci"
Requires-Dist: mypy; extra == "ci"
Dynamic: author
Dynamic: author-email
Dynamic: classifier
Dynamic: description
Dynamic: description-content-type
Dynamic: home-page
Dynamic: license
Dynamic: provides-extra
Dynamic: requires-dist
Dynamic: requires-python
Dynamic: summary
